odoo9_addon_stock_scanner-9.0.1.0.0-py2.7-nspkg.pth
odoo_addons/stock_scanner/__openerp__.py
odoo_addons/stock_scanner/load_scenario.py
odoo_addons/stock_scanner/__init__.py
odoo_addons/stock_scanner/README.rst
odoo_addons/stock_scanner/security/stock_scanner_security.xml
odoo_addons/stock_scanner/security/ir.model.access.csv
odoo_addons/stock_scanner/hardware/sentinel.py
odoo_addons/stock_scanner/hardware/odoo_sentinelrc.sample
odoo_addons/stock_scanner/hardware/i18n/translate.sh
odoo_addons/stock_scanner/hardware/i18n/en/LC_MESSAGES/sentinel.mo
odoo_addons/stock_scanner/hardware/i18n/sentinel/sentinel.pot
odoo_addons/stock_scanner/hardware/i18n/sentinel/en.po
odoo_addons/stock_scanner/hardware/i18n/sentinel/fr.po
odoo_addons/stock_scanner/hardware/i18n/fr/LC_MESSAGES/sentinel.mo
odoo_addons/stock_scanner/models/scanner_scenario_step.py
odoo_addons/stock_scanner/models/scanner_scenario_transition.py
odoo_addons/stock_scanner/models/scanner_hardware_step_history.py
odoo_addons/stock_scanner/models/scanner_scenario.py
odoo_addons/stock_scanner/models/__init__.py
odoo_addons/stock_scanner/models/scanner_scenario_custom.py
odoo_addons/stock_scanner/models/common.py
odoo_addons/stock_scanner/models/scanner_hardware.py
odoo_addons/stock_scanner/i18n/pt.po
odoo_addons/stock_scanner/i18n/it.po
odoo_addons/stock_scanner/i18n/es.po
odoo_addons/stock_scanner/i18n/tr.po
odoo_addons/stock_scanner/i18n/gl.po
odoo_addons/stock_scanner/i18n/ca.po
odoo_addons/stock_scanner/i18n/sl.po
odoo_addons/stock_scanner/i18n/es_ES.po
odoo_addons/stock_scanner/i18n/pt_PT.po
odoo_addons/stock_scanner/i18n/nl.po
odoo_addons/stock_scanner/i18n/am.po
odoo_addons/stock_scanner/i18n/de.po
odoo_addons/stock_scanner/i18n/fr.po
odoo_addons/stock_scanner/i18n/pt_BR.po
odoo_addons/stock_scanner/i18n/el_GR.po
odoo_addons/stock_scanner/i18n/fi.po
odoo_addons/stock_scanner/i18n/stock_scanner.pot
odoo_addons/stock_scanner/scripts/export_scenario.py
odoo9_addon_stock_scanner-9.0.1.0.0.dist-info/top_level.txt
odoo9_addon_stock_scanner-9.0.1.0.0.dist-info/WHEEL
odoo9_addon_stock_scanner-9.0.1.0.0.dist-info/RECORD
odoo9_addon_stock_scanner-9.0.1.0.0.dist-info/metadata.json
odoo9_addon_stock_scanner-9.0.1.0.0.dist-info/DESCRIPTION.rst
odoo9_addon_stock_scanner-9.0.1.0.0.dist-info/METADATA
odoo9_addon_stock_scanner-9.0.1.0.0.dist-info/namespace_packages.txt
